{
    "buses": [
      {
        "from": "New York",
        "to": "Los Angeles",
        "departure": "2025-04-10T08:00:00Z",
        "arrival": "2025-04-10T20:00:00Z",
        "price": 120,
        "busNumber": "NYLA101",
        "availableSeats": 45,
        "totalSeats": 50,
        "busType": "Luxury",
        "busCompany": "ABC Travels",
        "busImage": "https://source.unsplash.com/featured/?luxury-bus",
        "busDescription": "Luxury bus with reclining seats, WiFi, and entertainment."
      },
      {
        "from": "San Francisco",
        "to": "Las Vegas",
        "departure": "2025-04-11T09:30:00Z",
        "arrival": "2025-04-11T17:00:00Z",
        "price": 90,
        "busNumber": "SFLV205",
        "availableSeats": 20,
        "totalSeats": 40,
        "busType": "Semi-Sleeper",
        "busCompany": "RedLine",
        "busImage": "https://source.unsplash.com/featured/?bus",
        "busDescription": "Affordable comfort with semi-reclining seats and AC."
      },
      {
        "from": "Chicago",
        "to": "Detroit",
        "departure": "2025-04-12T06:00:00Z",
        "arrival": "2025-04-12T11:00:00Z",
        "price": 55,
        "busNumber": "CHIDT330",
        "availableSeats": 35,
        "totalSeats": 50,
        "busType": "AC",
        "busCompany": "GoBus",
        "busImage": "https://source.unsplash.com/featured/?ac-bus",
        "busDescription": "AC bus with good legroom and quick travel."
      },
      {
        "from": "Miami",
        "to": "Orlando",
        "departure": "2025-04-13T10:00:00Z",
        "arrival": "2025-04-13T15:00:00Z",
        "price": 70,
        "busNumber": "MIOR990",
        "availableSeats": 12,
        "totalSeats": 40,
        "busType": "Luxury",
        "busCompany": "BlueWave",
        "busImage": "https://source.unsplash.com/featured/?bus-travel",
        "busDescription": "Smooth ride with refreshments and charging ports."
      },
      {
        "from": "Dallas",
        "to": "Austin",
        "departure": "2025-04-10T07:00:00Z",
        "arrival": "2025-04-10T10:30:00Z",
        "price": 45,
        "busNumber": "DLAU880",
        "availableSeats": 25,
        "totalSeats": 35,
        "busType": "AC",
        "busCompany": "ExpressRoute",
        "busImage": "https://source.unsplash.com/featured/?express-bus",
        "busDescription": "Fast and comfortable travel at affordable price."
      },
      {
        "from": "Seattle",
        "to": "Portland",
        "departure": "2025-04-11T08:30:00Z",
        "arrival": "2025-04-11T12:30:00Z",
        "price": 60,
        "busNumber": "SEPO212",
        "availableSeats": 40,
        "totalSeats": 50,
        "busType": "Sleeper",
        "busCompany": "NorthStar",
        "busImage": "https://source.unsplash.com/featured/?sleeper-bus",
        "busDescription": "Sleeper bus for extra comfort on short journeys."
      },
      {
        "from": "Houston",
        "to": "San Antonio",
        "departure": "2025-04-12T14:00:00Z",
        "arrival": "2025-04-12T18:00:00Z",
        "price": 50,
        "busNumber": "HUSA305",
        "availableSeats": 10,
        "totalSeats": 30,
        "busType": "Semi-Sleeper",
        "busCompany": "QuickMove",
        "busImage": "https://source.unsplash.com/featured/?bus-inside",
        "busDescription": "Compact and fast, great for day trips."
      },
      {
        "from": "Boston",
        "to": "Philadelphia",
        "departure": "2025-04-10T13:00:00Z",
        "arrival": "2025-04-10T19:00:00Z",
        "price": 85,
        "busNumber": "BOPH703",
        "availableSeats": 22,
        "totalSeats": 40,
        "busType": "Luxury",
        "busCompany": "Comfort Travels",
        "busImage": "https://source.unsplash.com/featured/?luxury-coach",
        "busDescription": "Premium interiors with pushback seating and snacks."
      },
      {
        "from": "Atlanta",
        "to": "Charlotte",
        "departure": "2025-04-14T09:00:00Z",
        "arrival": "2025-04-14T13:30:00Z",
        "price": 65,
        "busNumber": "ATCH511",
        "availableSeats": 28,
        "totalSeats": 45,
        "busType": "AC",
        "busCompany": "StarBus",
        "busImage": "https://source.unsplash.com/featured/?chartered-bus",
        "busDescription": "Economical AC coach for regional travel."
      },
      {
        "from": "Denver",
        "to": "Salt Lake City",
        "departure": "2025-04-15T07:30:00Z",
        "arrival": "2025-04-15T16:00:00Z",
        "price": 95,
        "busNumber": "DELSC404",
        "availableSeats": 18,
        "totalSeats": 40,
        "busType": "Sleeper",
        "busCompany": "Mountain Movers",
        "busImage": "https://source.unsplash.com/featured/?bus-ride",
        "busDescription": "Great for long travel with comfort and breaks."
      }
    ]
  }
  